pylxc/__init__.py
pylxc/__main__.py
pylxc/liblxc/__init__.py
pylxc/liblxc/liblxc.py
pylxc_cli-0.0.9.dist-info/METADATA
pylxc_cli-0.0.9.dist-info/RECORD
pylxc_cli-0.0.9.dist-info/WHEEL
pylxc_cli-0.0.9.dist-info/entry_points.txt
pylxc_cli-0.0.9.dist-info/top_level.txt
