Metadata-Version: 2.1
Name: pylxc-cli
Version: 0.0.9
Summary: LXC client
Home-page: UNKNOWN
Author: pylxc
Author-email: vnaraujo@ciandt.com
License: UNKNOWN
Platform: UNKNOWN
Classifier: Development Status :: 2 - Pre-Alpha
Classifier: Environment :: Console
Classifier: License :: OSI Approved :: MIT License
Classifier: Natural Language :: English
Classifier: Operating System :: OS Independent
Classifier: Programming Language :: Python
Classifier: Programming Language :: Python :: 3
Classifier: Programming Language :: Python :: 3.5
Classifier: Topic :: Software Development :: Libraries :: Python Modules
Requires-Python: >=3
Requires-Dist: click (==6.7)
Requires-Dist: pylxd (==2.2.7)
